crawler/__init__.py
crawler/checkpoint.py
crawler/chunker.py
crawler/cli.py
crawler/content_extractor.py
crawler/crawler.py
crawler/fast_crawler.py
crawler/models.py
crawler/robots_parser.py
crawler/url_manager.py
llm_crawler-1.1.0.dist-info/licenses/LICENSE
llm_crawler-1.1.0.dist-info/METADATA
llm_crawler-1.1.0.dist-info/WHEEL
llm_crawler-1.1.0.dist-info/entry_points.txt
llm_crawler-1.1.0.dist-info/top_level.txt
llm_crawler-1.1.0.dist-info/RECORD
