Metadata-Version: 2.4
Name: llm-crawler
Version: 1.1.0
Summary: A web crawler CLI tool for preparing content for LLM ingestion and vector databases
Author: Arun Sunderraj
License-Expression: MIT
Project-URL: Homepage, https://github.com/Legolasan/llm-crawler
Project-URL: Repository, https://github.com/Legolasan/llm-crawler
Project-URL: Issues, https://github.com/Legolasan/llm-crawler/issues
Keywords: crawler,web-crawler,llm,vector-database,pgvector,rag,content-extraction,ai,machine-learning
Classifier: Development Status :: 4 - Beta
Classifier: Environment :: Console
Classifier: Intended Audience :: Developers
Classifier: Operating System :: OS Independent
Classifier: Programming Language :: Python :: 3
Classifier: Programming Language :: Python :: 3.10
Classifier: Programming Language :: Python :: 3.11
Classifier: Programming Language :: Python :: 3.12
Classifier: Programming Language :: Python :: 3.13
Classifier: Topic :: Internet :: WWW/HTTP :: Indexing/Search
Classifier: Topic :: Scientific/Engineering :: Artificial Intelligence
Classifier: Topic :: Text Processing :: Indexing
Requires-Python: >=3.10
License-File: LICENSE
Requires-Dist: playwright>=1.40.0
Requires-Dist: click>=8.1.0
Requires-Dist: beautifulsoup4>=4.12.0
Requires-Dist: lxml>=4.9.0
Requires-Dist: trafilatura>=1.6.0
Requires-Dist: html2text>=2020.1.16
Requires-Dist: tqdm>=4.66.0
Requires-Dist: validators>=0.22.0
Requires-Dist: requests>=2.31.0
Requires-Dist: httpx>=0.27.0
Requires-Dist: aiofiles>=23.0.0
Provides-Extra: dev
Requires-Dist: pytest>=7.4.0; extra == "dev"
Requires-Dist: pytest-asyncio>=0.21.0; extra == "dev"
Requires-Dist: pytest-cov>=4.1.0; extra == "dev"
Requires-Dist: black>=23.0.0; extra == "dev"
Requires-Dist: ruff>=0.1.0; extra == "dev"
Requires-Dist: mypy>=1.7.0; extra == "dev"
Requires-Dist: build>=1.0.0; extra == "dev"
Requires-Dist: twine>=4.0.0; extra == "dev"
Dynamic: license-file
